requirements_manager/__init__.py
requirements_manager/cli.py
requirements_manager/core.py
requirements_manager/utils.py
requirements_manager-0.1.2.dist-info/METADATA
requirements_manager-0.1.2.dist-info/WHEEL
requirements_manager-0.1.2.dist-info/entry_points.txt
requirements_manager-0.1.2.dist-info/licenses/LICENSE
requirements_manager-0.1.2.dist-info/RECORD
