Metadata-Version: 2.3
Name: requirements-manager
Version: 0.1.2
Summary: A tool to manage Python requirements files and their backups
Project-URL: Homepage, https://github.com/whoAmI-cslim/requirements_manager
Project-URL: Bug Tracker, https://github.com/whoAmI-cslim/requirements_manager/issues
Author-email: Clyde Hunter <clyde.hunter1984@gmail.com>
License-File: LICENSE
Classifier: License :: OSI Approved :: MIT License
Classifier: Operating System :: OS Independent
Classifier: Programming Language :: Python :: 3
Requires-Python: >=3.7
Requires-Dist: click>=8.0.0
